README.rst
setup.py
awesome_module.egg-info/PKG-INFO
awesome_module.egg-info/SOURCES.txt
awesome_module.egg-info/dependency_links.txt
awesome_module.egg-info/entry_points.txt
awesome_module.egg-info/top_level.txt
awesome_pip_module/__init__.py
awesome_pip_module/__main__.py
awesome_pip_module/awesome_module.py