Metadata-Version: 1.0
Name: awesome-module
Version: 0.1.0
Summary: Python command line html creator
Home-page: https://github.com/techin99/awesome_pip_module.git
Author: Brian Saminathen
Author-email: briansaminathen@hotmail.com
License: UNKNOWN
Platform: UNKNOWN
